FSM & TLC/moore_BCCB_nonoverlap.v
module moore_BCCB_nonoverlap(input clk,rst,valid, input [7:0]data_in, output reg seq_dec);
  
  parameter S_R 	= 5'b00001;
  parameter S_1 	= 5'b00010;
  parameter S_2 	= 5'b00100;
  parameter S_3 	= 5'b01000;
  parameter S_4 	= 5'b10000;
  
  reg [4:0] nxtstate,prestate;
  
  always@(posedge clk)begin
    if(rst) begin
      seq_dec=0;
      prestate = S_R;
      nxtstate = S_R;
    end
    else    prestate = nxtstate;
  end
  
  always@(*)begin
    if(valid) begin
 	  case(prestate)
 	    S_R:begin
          seq_dec=0;
          if(data_in=="B")  	 nxtstate=S_1;
          else if(data_in=="C")  nxtstate=S_R;
          else 					 nxtstate=S_R;
 	    end   
        S_1:begin
          seq_dec=0;
          if(data_in=="B")  	 nxtstate=S_1;
          else if(data_in=="C")  nxtstate=S_2;
          else 					 nxtstate=S_R;
 	    end   
        S_2:begin
          seq_dec=0;
          if(data_in=="B")  	 nxtstate=S_1;
          else if(data_in=="C")  nxtstate=S_3;
          else 					 nxtstate=S_R;
 	    end   
        S_3:begin
          seq_dec=0;
          if(data_in=="B")  	 nxtstate=S_4;
          else if(data_in=="C")  nxtstate=S_R;
          else 					 nxtstate=S_R;
 	    end   
        S_4:begin
          seq_dec=1;
          if(data_in=="B")  	 nxtstate=S_1;
          else if(data_in=="C")  nxtstate=S_R;
          else 					 nxtstate=S_R;
 	 	end
      endcase
    end
  end
endmodule

module tb; 
  reg clk=0;
  reg rst,valid;
  reg [7:0] data_in;
  //reg [1000:0] ip_data = "BCCBuguighusghgBBBCBCBBBAFFGJDBBCBBCBB:)";
  wire seq_dec;
  
  integer  count;
  
  moore_BCCB_nonoverlap dut(.clk(clk), .rst(rst), .valid(valid), .data_in(data_in), .seq_dec(seq_dec));
  
  always #5 clk=~clk;
  
  initial begin
    count=0;
    rst=1;
    valid=0;
    repeat(2)@(posedge clk);
    rst=0;
    repeat(50) begin
      @(posedge clk);
      valid=1;
      data_in=$urandom_range(65,67);
      $write("%0c",data_in);
      @(posedge clk);
      valid=0;
      data_in=0;
    end 
      @(posedge clk);
      valid=1;
      data_in="B";
      $write("%0c",data_in);
      @(posedge clk);
      valid=0;
      data_in=0; 
    @(posedge clk);
      valid=1;
      data_in="C";
      $write("%0c",data_in);
      @(posedge clk);
      valid=0;
      data_in=0; 
    @(posedge clk);
      valid=1;
      data_in="C";
      $write("%0c",data_in);
      @(posedge clk);
      valid=0;
      data_in=0; 
    @(posedge clk);
      valid=1;
      data_in="B";
      $write("%0c",data_in);
      @(posedge clk);
      valid=0;
      data_in=0; 
    @(posedge clk);
      valid=1;
      data_in="C";
      $write("%0c",data_in);
      @(posedge clk);
      valid=0;
      data_in=0; 
    @(posedge clk);
      valid=1;
      data_in="C";
      $write("%0c",data_in);
      @(posedge clk);
      valid=0;
      data_in=0; 
    @(posedge clk);
      valid=1;
      data_in="B";
      $write("%0c",data_in);
      @(posedge clk);
      valid=0;
      data_in=0; 
    @(posedge clk);
      valid=1;
      data_in="B";
      $write("%0c",data_in);
      @(posedge clk);
      valid=0;
      data_in=0;
  end
  
  always @(posedge seq_dec) count = count + 1;
  
  initial begin
    $dumpfile("dump.vcd"); $dumpvars;
    #1500;
    $display("Total no 101101 sequence detected is %0d",count);
    #10;
    $finish();
  end
endmodule

FSM & TLC/dump.vcd
$date
	Sat Mar  8 04:04:47 2025
$end
$version
	QuestaSim Version 2024.3_1
$end
$timescale
	1ns
$end

$scope module tb $end
$var integer 32 ! count $end
$var wire 1 " seq_dec $end
$var reg 1 # clk $end
$var reg 8 $ data_in [7:0] $end
$var reg 1 % rst $end
$var reg 1 & valid $end

$scope module dut $end
$var wire 1 ' clk $end
$var wire 1 ( data_in [7] $end
$var wire 1 ) data_in [6] $end
$var wire 1 * data_in [5] $end
$var wire 1 + data_in [4] $end
$var wire 1 , data_in [3] $end
$var wire 1 - data_in [2] $end
$var wire 1 . data_in [1] $end
$var wire 1 / data_in [0] $end
$var wire 1 0 rst $end
$var wire 1 1 valid $end
$var parameter 5 2 S_1 $end
$var parameter 5 3 S_2 $end
$var parameter 5 4 S_3 $end
$var parameter 5 5 S_4 $end
$var parameter 5 6 S_R $end
$var reg 5 7 nxtstate [4:0] $end
$var reg 5 8 prestate [4:0] $end
$var reg 1 9 seq_dec $end
$upscope $end
$upscope $end

$scope begin std $end
$upscope $end
$enddefinitions $end
#0
$dumpvars
0"
x/
x.
x-
x,
x+
x*
x)
x(
01
10
0'
b0 !
0#
bx $
1%
0&
b10 2
b100 3
b1000 4
b10000 5
b1 6
bx 7
bx 8
09
$end
#5
1#
1'
b1 8
b1 7
#10
0#
0'
#15
1#
1'
0%
00
#20
0#
0'
#25
1#
1'
1&
b1000011 $
11
1/
1.
0-
0,
0+
0*
1)
0(
#30
0#
0'
#35
1#
1'
0&
b0 $
01
0/
0.
0)
#40
0#
0'
#45
1#
1'
1&
b1000010 $
11
1.
1)
b10 7
#50
0#
0'
#55
1#
1'
b10 8
0&
b0 $
01
0.
0)
#60
0#
0'
#65
1#
1'
1&
b1000010 $
11
1.
1)
b100 7
#70
0#
0'
#75
1#
1'
b100 8
0&
b0 $
01
0.
0)
#80
0#
0'
#85
1#
1'
1&
b1000010 $
11
1.
1)
#90
0#
0'
#95
1#
1'
0&
b0 $
01
0.
0)
#100
0#
0'
#105
1#
1'
1&
b1000010 $
11
1.
1)
#110
0#
0'
#115
1#
1'
0&
b0 $
01
0.
0)
#120
0#
0'
#125
1#
1'
1&
b1000010 $
11
1.
1)
#130
0#
0'
#135
1#
1'
0&
b0 $
01
0.
0)
#140
0#
0'
#145
1#
1'
1&
b1000011 $
11
1/
1.
1)
b1000 7
#150
0#
0'
#155
1#
1'
b1000 8
0&
b0 $
01
0/
0.
0)
#160
0#
0'
#165
1#
1'
1&
b1000011 $
11
1/
1.
1)
b1 7
#170
0#
0'
#175
1#
1'
b1 8
0&
b0 $
01
0/
0.
0)
#180
0#
0'
#185
1#
1'
1&
b1000010 $
11
1.
1)
b10 7
#190
0#
0'
#195
1#
1'
b10 8
0&
b0 $
01
0.
0)
#200
0#
0'
#205
1#
1'
1&
b1000011 $
11
1/
1.
1)
b1 7
#210
0#
0'
#215
1#
1'
b1 8
0&
b0 $
01
0/
0.
0)
#220
0#
0'
#225
1#
1'
1&
b1000011 $
11
1/
1.
1)
#230
0#
0'
#235
1#
1'
0&
b0 $
01
0/
0.
0)
#240
0#
0'
#245
1#
1'
1&
b1000011 $
11
1/
1.
1)
#250
0#
0'
#255
1#
1'
0&
b0 $
01
0/
0.
0)
#260
0#
0'
#265
1#
1'
1&
b1000011 $
11
1/
1.
1)
#270
0#
0'
#275
1#
1'
0&
b0 $
01
0/
0.
0)
#280
0#
0'
#285
1#
1'
1&
b1000010 $
11
1.
1)
b10 7
#290
0#
0'
#295
1#
1'
b10 8
0&
b0 $
01
0.
0)
#300
0#
0'
#305
1#
1'
1&
b1000010 $
11
1.
1)
b100 7
#310
0#
0'
#315
1#
1'
b100 8
0&
b0 $
01
0.
0)
#320
0#
0'
#325
1#
1'
1&
b1000010 $
11
1.
1)
#330
0#
0'
#335
1#
1'
0&
b0 $
01
0.
0)
#340
0#
0'
#345
1#
1'
1&
b1000010 $
11
1.
1)
#350
0#
0'
#355
1#
1'
0&
b0 $
01
0.
0)
#360
0#
0'
#365
1#
1'
1&
b1000010 $
11
1.
1)
#370
0#
0'
#375
1#
1'
0&
b0 $
01
0.
0)
#380
0#
0'
#385
1#
1'
1&
b1000010 $
11
1.
1)
#390
0#
0'
#395
1#
1'
0&
b0 $
01
0.
0)
#400
0#
0'
#405
1#
1'
1&
b1000011 $
11
1/
1.
1)
b1000 7
#410
0#
0'
#415
1#
1'
b1000 8
0&
b0 $
01
0/
0.
0)
#420
0#
0'
#425
1#
1'
1&
b1000011 $
11
1/
1.
1)
b1 7
#430
0#
0'
#435
1#
1'
b1 8
0&
b0 $
01
0/
0.
0)
#440
0#
0'
#445
1#
1'
1&
b1000011 $
11
1/
1.
1)
#450
0#
0'
#455
1#
1'
0&
b0 $
01
0/
0.
0)
#460
0#
0'
#465
1#
1'
1&
b1000010 $
11
1.
1)
b10 7
#470
0#
0'
#475
1#
1'
b10 8
0&
b0 $
01
0.
0)
#480
0#
0'
#485
1#
1'
1&
b1000010 $
11
1.
1)
b100 7
#490
0#
0'
#495
1#
1'
b100 8
0&
b0 $
01
0.
0)
#500
0#
0'
#505
1#
1'
1&
b1000011 $
11
1/
1.
1)
b1000 7
#510
0#
0'
#515
1#
1'
b1000 8
0&
b0 $
01
0/
0.
0)
#520
0#
0'
#525
1#
1'
1&
b1000011 $
11
1/
1.
1)
b1 7
#530
0#
0'
#535
1#
1'
b1 8
0&
b0 $
01
0/
0.
0)
#540
0#
0'
#545
1#
1'
1&
b1000010 $
11
1.
1)
b10 7
#550
0#
0'
#555
1#
1'
b10 8
0&
b0 $
01
0.
0)
#560
0#
0'
#565
1#
1'
1&
b1000010 $
11
1.
1)
b100 7
#570
0#
0'
#575
1#
1'
b100 8
0&
b0 $
01
0.
0)
#580
0#
0'
#585
1#
1'
1&
b1000011 $
11
1/
1.
1)
b1000 7
#590
0#
0'
#595
1#
1'
b1000 8
0&
b0 $
01
0/
0.
0)
#600
0#
0'
#605
1#
1'
1&
b1000010 $
11
1.
1)
b10000 7
#610
0#
0'
#615
1#
1'
b10000 8
0&
b0 $
01
0.
0)
#620
0#
0'
#625
1#
1'
1&
b1000011 $
11
1/
1.
1)
b1 7
19
1"
b1 !
#630
0#
0'
#635
1#
1'
b1 8
0&
b0 $
01
0/
0.
0)
09
0"
#640
0#
0'
#645
1#
1'
1&
b1000011 $
11
1/
1.
1)
#650
0#
0'
#655
1#
1'
0&
b0 $
01
0/
0.
0)
#660
0#
0'
#665
1#
1'
1&
b1000010 $
11
1.
1)
b10 7
#670
0#
0'
#675
1#
1'
b10 8
0&
b0 $
01
0.
0)
#680
0#
0'
#685
1#
1'
1&
b1000010 $
11
1.
1)
b100 7
#690
0#
0'
#695
1#
1'
b100 8
0&
b0 $
01
0.
0)
#700
0#
0'
#705
1#
1'
1&
b1000011 $
11
1/
1.
1)
b1000 7
#710
0#
0'
#715
1#
1'
b1000 8
0&
b0 $
01
0/
0.
0)
#720
0#
0'
#725
1#
1'
1&
b1000010 $
11
1.
1)
b10000 7
#730
0#
0'
#735
1#
1'
b10000 8
0&
b0 $
01
0.
0)
#740
0#
0'
#745
1#
1'
1&
b1000010 $
11
1.
1)
b100 7
#750
0#
0'
#755
1#
1'
b100 8
0&
b0 $
01
0.
0)
#760
0#
0'
#765
1#
1'
1&
b1000010 $
11
1.
1)
#770
0#
0'
#775
1#
1'
0&
b0 $
01
0.
0)
#780
0#
0'
#785
1#
1'
1&
b1000011 $
11
1/
1.
1)
b1000 7
#790
0#
0'
#795
1#
1'
b1000 8
0&
b0 $
01
0/
0.
0)
#800
0#
0'
#805
1#
1'
1&
b1000010 $
11
1.
1)
b10000 7
#810
0#
0'
#815
1#
1'
b10000 8
0&
b0 $
01
0.
0)
#820
0#
0'
#825
1#
1'
1&
b1000011 $
11
1/
1.
1)
b1 7
19
1"
b10 !
#830
0#
0'
#835
1#
1'
b1 8
0&
b0 $
01
0/
0.
0)
09
0"
#840
0#
0'
#845
1#
1'
1&
b1000010 $
11
1.
1)
b10 7
#850
0#
0'
#855
1#
1'
b10 8
0&
b0 $
01
0.
0)
#860
0#
0'
#865
1#
1'
1&
b1000010 $
11
1.
1)
b100 7
#870
0#
0'
#875
1#
1'
b100 8
0&
b0 $
01
0.
0)
#880
0#
0'
#885
1#
1'
1&
b1000011 $
11
1/
1.
1)
b1000 7
#890
0#
0'
#895
1#
1'
b1000 8
0&
b0 $
01
0/
0.
0)
#900
0#
0'
#905
1#
1'
1&
b1000011 $
11
1/
1.
1)
b1 7
#910
0#
0'
#915
1#
1'
b1 8
0&
b0 $
01
0/
0.
0)
#920
0#
0'
#925
1#
1'
1&
b1000010 $
11
1.
1)
b10 7
#930
0#
0'
#935
1#
1'
b10 8
0&
b0 $
01
0.
0)
#940
0#
0'
#945
1#
1'
1&
b1000011 $
11
1/
1.
1)
b1 7
#950
0#
0'
#955
1#
1'
b1 8
0&
b0 $
01
0/
0.
0)
#960
0#
0'
#965
1#
1'
1&
b1000011 $
11
1/
1.
1)
#970
0#
0'
#975
1#
1'
0&
b0 $
01
0/
0.
0)
#980
0#
0'
#985
1#
1'
1&
b1000010 $
11
1.
1)
b10 7
#990
0#
0'
#995
1#
1'
b10 8
0&
b0 $
01
0.
0)
#1000
0#
0'
#1005
1#
1'
1&
b1000011 $
11
1/
1.
1)
b1 7
#1010
0#
0'
#1015
1#
1'
b1 8
0&
b0 $
01
0/
0.
0)
#1020
0#
0'
#1025
1#
1'
1&
b1000010 $
11
1.
1)
b10 7
#1030
0#
0'
#1035
1#
1'
b10 8
0&
b0 $
01
0.
0)
#1040
0#
0'
#1045
1#
1'
1&
b1000011 $
11
1/
1.
1)
b1 7
#1050
0#
0'
#1055
1#
1'
b1 8
0&
b0 $
01
0/
0.
0)
#1060
0#
0'
#1065
1#
1'
1&
b1000011 $
11
1/
1.
1)
#1070
0#
0'
#1075
1#
1'
0&
b0 $
01
0/
0.
0)
#1080
0#
0'
#1085
1#
1'
1&
b1000011 $
11
1/
1.
1)
#1090
0#
0'
#1095
1#
1'
0&
b0 $
01
0/
0.
0)
#1100
0#
0'
#1105
1#
1'
1&
b1000010 $
11
1.
1)
b10 7
#1110
0#
0'
#1115
1#
1'
b10 8
0&
b0 $
01
0.
0)
#1120
0#
0'
#1125
1#
1'
1&
b1000010 $
11
1.
1)
b100 7
#1130
0#
0'
#1135
1#
1'
b100 8
0&
b0 $
01
0.
0)
#1140
0#
0'
#1145
1#
1'
1&
b1000010 $
11
1.
1)
#1150
0#
0'
#1155
1#
1'
0&
b0 $
01
0.
0)
#1160
0#
0'
#1165
1#
1'
1&
b1000011 $
11
1/
1.
1)
b1000 7
#1170
0#
0'
#1175
1#
1'
b1000 8
0&
b0 $
01
0/
0.
0)
#1180
0#
0'
#1185
1#
1'
1&
b1000010 $
11
1.
1)
b10000 7
#1190
0#
0'
#1195
1#
1'
b10000 8
0&
b0 $
01
0.
0)
#1200
0#
0'
#1205
1#
1'
1&
b1000011 $
11
1/
1.
1)
b1 7
19
1"
b11 !
#1210
0#
0'
#1215
1#
1'
b1 8
0&
b0 $
01
0/
0.
0)
09
0"
#1220
0#
0'
#1225
1#
1'
1&
b1000011 $
11
1/
1.
1)
#1230
0#
0'
#1235
1#
1'
0&
b0 $
01
0/
0.
0)
#1240
0#
0'
#1245
1#
1'
1&
b1000011 $
11
1/
1.
1)
#1250
0#
0'
#1255
1#
1'
0&
b0 $
01
0/
0.
0)
#1260
0#
0'
#1265
1#
1'
1&
b1000010 $
11
1.
1)
b10 7
#1270
0#
0'
#1275
1#
1'
b10 8
0&
b0 $
01
0.
0)
#1280
0#
0'
#1285
1#
1'
1&
b1000011 $
11
1/
1.
1)
b1 7
#1290
0#
0'
#1295
1#
1'
b1 8
0&
b0 $
01
0/
0.
0)
#1300
0#
0'
#1305
1#
1'
1&
b1000011 $
11
1/
1.
1)
#1310
0#
0'
#1315
1#
1'
0&
b0 $
01
0/
0.
0)
#1320
0#
0'
#1325
1#
1'
1&
b1000011 $
11
1/
1.
1)
#1330
0#
0'
#1335
1#
1'
0&
b0 $
01
0/
0.
0)
#1340
0#
0'
#1345
1#
1'
1&
b1000010 $
11
1.
1)
b10 7
#1350
0#
0'
#1355
1#
1'
b10 8
0&
b0 $
01
0.
0)
#1360
0#
0'
#1365
1#
1'
1&
b1000010 $
11
1.
1)
b100 7
#1370
0#
0'
#1375
1#
1'
b100 8
0&
b0 $
01
0.
0)
#1380
0#
0'
#1385
1#
1'
1&
b1000010 $
11
1.
1)
#1390
0#
0'
#1395
1#
1'
0&
b0 $
01
0.
0)
#1400
0#
0'
#1405
1#
1'
1&
b1000011 $
11
1/
1.
1)
b1000 7
#1410
0#
0'
#1415
1#
1'
b1000 8
0&
b0 $
01
0/
0.
0)
#1420
0#
0'
#1425
1#
1'
1&
b1000010 $
11
1.
1)
b10000 7
#1430
0#
0'
#1435
1#
1'
b10000 8
0&
b0 $
01
0.
0)
#1440
0#
0'
#1445
1#
1'
1&
b1000011 $
11
1/
1.
1)
b1 7
19
1"
b100 !
#1450
0#
0'
#1455
1#
1'
b1 8
0&
b0 $
01
0/
0.
0)
09
0"
#1460
0#
0'
#1465
1#
1'
1&
b1000010 $
11
1.
1)
b10 7
#1470
0#
0'
#1475
1#
1'
b10 8
0&
b0 $
01
0.
0)
#1480
0#
0'
#1485
1#
1'
1&
b1000011 $
11
1/
1.
1)
b1 7
#1490
0#
0'
#1495
1#
1'
b1 8
0&
b0 $
01
0/
0.
0)
#1500
0#
0'
#1505
1#
1'
1&
b1000010 $
11
1.
1)
b10 7
